atenigma/__init__.py
atenigma/banner.py
atenigma/decryption.py
atenigma/encryption.py
atenigma/main.py
ATENIGMA-0.1.4.dist-info/METADATA
ATENIGMA-0.1.4.dist-info/WHEEL
ATENIGMA-0.1.4.dist-info/entry_points.txt
ATENIGMA-0.1.4.dist-info/top_level.txt
ATENIGMA-0.1.4.dist-info/RECORD
